rdktools/__init__.py
rdktools/db/App.py
rdktools/db/Utils.py
rdktools/db/__init__.py
rdktools/depict/App.py
rdktools/depict/DepictCgi.py
rdktools/depict/Mol2ImgCgi.py
rdktools/depict/MolAlign.py
rdktools/depict/Utils.py
rdktools/depict/__init__.py
rdktools/dgeom/App.py
rdktools/dgeom/DgeomCgi.py
rdktools/dgeom/Utils.py
rdktools/dgeom/__init__.py
rdktools/formats/App.py
rdktools/formats/Utils.py
rdktools/formats/__init__.py
rdktools/fp/App.py
rdktools/fp/ClusterMols.py
rdktools/fp/Extras.py
rdktools/fp/FingerprintMols.py
rdktools/fp/MolSimilarity.py
rdktools/fp/Utils.py
rdktools/fp/__init__.py
rdktools/mcs/App.py
rdktools/mcs/Utils.py
rdktools/mcs/__init__.py
rdktools/properties/App.py
rdktools/properties/Utils.py
rdktools/properties/__init__.py
rdktools/reactions/App.py
rdktools/reactions/Utils.py
rdktools/reactions/__init__.py
rdktools/scaffold/App.py
rdktools/scaffold/Utils.py
rdktools/scaffold/__init__.py
rdktools/smarts/App.py
rdktools/smarts/SmartsFile.py
rdktools/smarts/Utils.py
rdktools/smarts/__init__.py
rdktools/standard/App.py
rdktools/standard/Utils.py
rdktools/standard/__init__.py
rdktools/util/Cansmi.py
rdktools/util/Utils.py
rdktools/util/View3dJsmolCgi.py
rdktools/util/__init__.py
rdktools/util/db/Utils.py
rdktools/util/db/__init__.py
rdktools/util/http/Utils.py
rdktools/util/http/__init__.py
rdktools/util/http/env_cgi.py
rdktools/util/http/mol2imghtm.py
rdktools/util/http/purgescratchdirs.py
rdktools/util/latex/Utils.py
rdktools/util/latex/__init__.py
rdktools/util/mp/Utils.py
rdktools/util/mp/__init__.py
rdktools/util/sklearn/ClusterFingerprints.py
rdktools/util/sklearn/__init__.py
rdktools/util/yaml/Utils.py
rdktools/util/yaml/__init__.py
rdktools-0.9.8.dist-info/METADATA
rdktools-0.9.8.dist-info/WHEEL
rdktools-0.9.8.dist-info/top_level.txt
rdktools-0.9.8.dist-info/RECORD
