Metadata-Version: 2.1
Name: rdktools
Version: 0.9.8
Summary: Tools and helpers for RDKit.
Home-page: https://github.com/jeremyjyang/rdkit-tools
Author: Jeremy Yang
Author-email: jeremyjyang@gmail.com
License: UNKNOWN
Platform: UNKNOWN
Classifier: Programming Language :: Python :: 3
Classifier: License :: OSI Approved :: MIT License
Classifier: Operating System :: OS Independent
Requires-Python: >=3.8
